LICENSE.txt
MANIFEST.in
README.md
setup.cfg
setup.py
kdr/__init__.py
kdr/cli.py
kdr/cli_syncthing_adapter.py
kdr/platform_adapter.py
kdr/syncthing_factory.py
kdr.egg-info/PKG-INFO
kdr.egg-info/SOURCES.txt
kdr.egg-info/dependency_links.txt
kdr.egg-info/entry_points.txt
kdr.egg-info/not-zip-safe
kdr.egg-info/requires.txt
kdr.egg-info/top_level.txt
kdr/data/__init__.py
kdr/data/config.py
kdr/data/custom_errors.py
kdr/data/mac_plist_adt.py
kdr/data/syncthing_adt.py
kdr/py_syncthing_adapter/__init__.py
kdr/utils/__init__.py
kdr/utils/config_rollbacker.py
static/linux/kdr
tests/mock/__init__.py
tests/mock/adapters.py
tests/mock/cli.py